requestor.py
requestor-0.1.1.dist-info/DESCRIPTION.rst
requestor-0.1.1.dist-info/METADATA
requestor-0.1.1.dist-info/RECORD
requestor-0.1.1.dist-info/WHEEL
requestor-0.1.1.dist-info/metadata.json
requestor-0.1.1.dist-info/top_level.txt
